llama_index/tools/playgrounds/__init__.py
llama_index/tools/playgrounds/subgraph_connector/__init__.py
llama_index/tools/playgrounds/subgraph_connector/base.py
llama_index/tools/playgrounds/subgraph_inspector/__init__.py
llama_index/tools/playgrounds/subgraph_inspector/base.py
llama_index_tools_playgrounds-0.4.1.dist-info/METADATA
llama_index_tools_playgrounds-0.4.1.dist-info/WHEEL
llama_index_tools_playgrounds-0.4.1.dist-info/licenses/LICENSE
llama_index_tools_playgrounds-0.4.1.dist-info/RECORD
