Metadata-Version: 2.4
Name: llama-index-tools-playgrounds
Version: 0.4.1
Summary: llama-index tools playgrounds integration
Author-email: Your Name <you@example.com>
Maintainer: tachi
License-Expression: MIT
License-File: LICENSE
Keywords: blockchain,decentralized,graphql,playgroundsapi,subgraph,thegraph
Requires-Python: <4.0,>=3.9
Requires-Dist: llama-index-core<0.15,>=0.13.0
Requires-Dist: llama-index-tools-graphql<0.5,>=0.4.0
